[
  {
    "id": 1,
    "olympic_year": 2028,
    "host_city": "Los Angeles, USA",
    "flag_football_status": "demonstration_sport",
    "anti_doping_compliance": [
      "wada_standards",
      "real_time_monitoring",
      "athlete_education"
    ],
    "international_standards_application": [
      "olympic_charter",
      "ifaf_regulations",
      "world_anti_doping_code"
    ],
    "cultural_dietary_considerations": [
      "multicultural_nutrition",
      "religious_dietary_laws",
      "local_food_integration"
    ],
    "wearable_technology_integration": true,
    "real_time_biometric_monitoring": true,
    "ai_powered_hydration_optimization": true,
    "research_collaborations": [
      "olympic_research_center",
      "university_partnerships",
      "international_studies"
    ],
    "knowledge_transfer_programs": [
      "coach_education",
      "athlete_mentorship",
      "sports_science_exchange"
    ],
    "long_term_impact_studies": true,
    "created_at": "2025-08-17T19:48:27.314Z"
  }
]
