[
  {
    "id": 1,
    "quote_text": "Champions aren't made in comfort zones. Today's training is tomorrow's victory.",
    "author": "Coach Marcus Rivera",
    "category": "motivation",
    "is_active": true,
    "created_at": "2025-08-31T08:28:59.824Z"
  },
  {
    "id": 2,
    "quote_text": "The difference between ordinary and extraordinary is that little extra.",
    "author": "Jimmy Johnson",
    "category": "motivation",
    "is_active": true,
    "created_at": "2025-08-31T08:28:59.824Z"
  },
  {
    "id": 3,
    "quote_text": "Success is no accident. It is hard work, perseverance, learning, studying, sacrifice and most of all, love of what you are doing.",
    "author": "Pelé",
    "category": "motivation",
    "is_active": true,
    "created_at": "2025-08-31T08:28:59.824Z"
  }
]